lacrei_models/__init__.py
lacrei_models/address/__init__.py
lacrei_models/address/fixtures/address.json
lacrei_models/address/models.py
lacrei_models/appointments/__init__.py
lacrei_models/appointments/models.py
lacrei_models/client/__init__.py
lacrei_models/client/fixtures/__init__.py
lacrei_models/client/fixtures/client-intersectionality.json
lacrei_models/client/fixtures/client-privacy-docs.json
lacrei_models/client/fixtures/sites-dev.json
lacrei_models/client/fixtures/sites-production.json
lacrei_models/client/fixtures/sites-sandbox.json
lacrei_models/client/fixtures/sites-staging.json
lacrei_models/client/managers.py
lacrei_models/client/models.py
lacrei_models/notification/__init__.py
lacrei_models/notification/models.py
lacrei_models/payments/__init__.py
lacrei_models/payments/models.py
lacrei_models/professional/__init__.py
lacrei_models/professional/fixtures/__init__.py
lacrei_models/professional/fixtures/professional.json
lacrei_models/professional/models.py
lacrei_models/professional/services/__init__.py
lacrei_models/professional/services/verification.py
lacrei_models/sync/__init__.py
lacrei_models/sync/models.py
lacrei_models/utils/__init__.py
lacrei_models/utils/models.py
lacrei_models/utils/social_choices.py
lacrei_models/utils/validators.py
lacrei_models-3.0.0.dist-info/METADATA
lacrei_models-3.0.0.dist-info/WHEEL
lacrei_models-3.0.0.dist-info/RECORD
