Metadata-Version: 2.4
Name: lacrei-models
Version: 3.0.0
Summary: Modelos de domínio do projeto Lacrei.
Author: Kaio
Author-email: kaioherculano12@gmail.com
Requires-Python: >=3.11,<4
Classifier: Programming Language :: Python :: 3
Classifier: Programming Language :: Python :: 3.11
Classifier: Programming Language :: Python :: 3.12
Classifier: Programming Language :: Python :: 3.13
Classifier: Programming Language :: Python :: 3.14
Requires-Dist: celery (>=5.5.3,<6.0.0)
Requires-Dist: django (>=4.0)
Requires-Dist: django-allauth (>=65.4.1,<66.0.0)
Requires-Dist: django-environ (>=0.12.0,<0.13.0)
Requires-Dist: django-phonenumber-field (>=8.1.0,<9.0.0)
Requires-Dist: django-watson (>=1.6.3,<2.0.0)
Requires-Dist: djangorestframework (>=3.16.1,<4.0.0)
Requires-Dist: dnspython (>=2.8.0,<3.0.0)
Requires-Dist: inlinestyler (>=0.2.5,<0.3.0)
Requires-Dist: phonenumbers (>=9.0.14,<10.0.0)
Requires-Dist: psycopg2-binary (>=2.9.10,<3.0.0)
Requires-Dist: pydantic (>=2.11.9,<3.0.0)
Requires-Dist: requests (>=2.32.3,<3.0.0)
